[
  {
    "id": 1,
    "title": "Example emergency (without geo area)",
    "geo_areas": [],
    "is_active": true,
    "streets": [],
    "created_at": "2017-01-19T00:12:29+0100"
  },
  {
    "id": 3,
    "title": "test-emergency",
    "geo_areas": [
      {
        "geo_points": [
          {
            "lng": 6.8053436279297,
            "lat": 50.936904512934,
            "position": 0
          },
          {
            "lng": 6.7856025695801,
            "lat": 50.920891583065,
            "position": 1
          },
          {
            "lng": 6.7998504638672,
            "lat": 50.905197893286,
            "position": 2
          },
          {
            "lng": 6.9225883483887,
            "lat": 50.903790614326,
            "position": 3
          },
          {
            "lng": 6.9406127929688,
            "lat": 50.916887489245,
            "position": 4
          },
          {
            "lng": 6.9232749938965,
            "lat": 50.935714552369,
            "position": 5
          },
          {
            "lng": 6.8607902526855,
            "lat": 50.919592995795,
            "position": 6
          }
        ]
      }
    ],
    "is_active": true,
    "streets": [],
    "created_at": "2017-01-26T11:49:05+0100"
  },
  {
    "id": 4,
    "title": "emergency with three geo-areas",
    "geo_areas": [
      {
        "geo_points": [
          {
            "lng": 6.7773628234863,
            "lat": 50.936471803525,
            "position": 0
          },
          {
            "lng": 6.7734146118164,
            "lat": 50.916021693926,
            "position": 1
          },
          {
            "lng": 6.7833709716797,
            "lat": 50.915588790227,
            "position": 2
          },
          {
            "lng": 6.7866325378418,
            "lat": 50.92457071685,
            "position": 3
          }
        ]
      },
      {
        "geo_points": [
          {
            "lng": 6.815128326416,
            "lat": 50.935173651136,
            "position": 4
          },
          {
            "lng": 6.8127250671387,
            "lat": 50.916346369059,
            "position": 5
          },
          {
            "lng": 6.8278312683105,
            "lat": 50.917320380864,
            "position": 6
          },
          {
            "lng": 6.8292045593262,
            "lat": 50.935390012384,
            "position": 7
          }
        ]
      },
      {
        "geo_points": [
          {
            "lng": 6.8803596496582,
            "lat": 50.934849107377,
            "position": 8
          },
          {
            "lng": 6.9011306762695,
            "lat": 50.934957288882,
            "position": 9
          },
          {
            "lng": 6.8822479248047,
            "lat": 50.91580524258,
            "position": 10
          },
          {
            "lng": 6.8789863586426,
            "lat": 50.92576096255,
            "position": 11
          },
          {
            "lng": 6.8645668029785,
            "lat": 50.925219945552,
            "position": 12
          },
          {
            "lng": 6.8642234802246,
            "lat": 50.929872486116,
            "position": 13
          },
          {
            "lng": 6.8762397766113,
            "lat": 50.929656099199,
            "position": 14
          }
        ]
      }
    ],
    "is_active": true,
    "streets": [],
    "created_at": "2017-01-26T11:55:10+0100"
  }
]